curtxt.py
curtxt_reader-1.2.4.dist-info/LICENSE
curtxt_reader-1.2.4.dist-info/METADATA
curtxt_reader-1.2.4.dist-info/WHEEL
curtxt_reader-1.2.4.dist-info/entry_points.txt
curtxt_reader-1.2.4.dist-info/top_level.txt
curtxt_reader-1.2.4.dist-info/RECORD
