Metadata-Version: 2.1
Name: curtxt-reader
Version: 1.2.4
Summary: A simple ncurses-based plain text reader
Author-email: 1256-bits <128bit@eclipso.eu>
License: Mozilla Public License Version 2.0
Project-URL: Homepage, https://github.com/1256-bits/curses-txt-reader
Project-URL: Source, https://github.com/1256-bits/curses-txt-reader
Keywords: reader,plain text,txt,text,ncurses
Classifier: License :: OSI Approved :: Mozilla Public License 2.0 (MPL 2.0)
Classifier: Programming Language :: Python
Classifier: Programming Language :: Python :: 3
Classifier: Development Status :: 5 - Production/Stable
Classifier: Environment :: Console :: Curses
Classifier: Intended Audience :: End Users/Desktop
Requires-Python: >=3.10
License-File: LICENSE
